commands/__init__.py
commands/base.py
commands/exceptions.py
commands/invoker.py
commands/validators.py
tests/__init__.py
tests/fixtures/__init__.py
tests/fixtures/fake_commands.py
tests/test_commands/__init__.py
tests/test_commands/test_base_command.py
tests/test_commands/test_invokers.py
tests/test_commands/test_validators.py
pycommands-0.1.0.dist-info/LICENSE
pycommands-0.1.0.dist-info/METADATA
pycommands-0.1.0.dist-info/WHEEL
pycommands-0.1.0.dist-info/top_level.txt
pycommands-0.1.0.dist-info/RECORD
