Metadata-Version: 2.1
Name: pycommands
Version: 0.1.0
Summary: Handle a list of commands that should be executed easily and with undo support.
Home-page: https://github.com/rafaelcassau/pycommands
Author: Rafael Cassau
Author-email: rafa.cassau@gmail.com
License: UNKNOWN
Platform: UNKNOWN
Classifier: Programming Language :: Python :: 3
Classifier: License :: OSI Approved :: MIT License
Classifier: Operating System :: OS Independent
Requires-Python: >=3.7
